specktre/__init__.py
specktre/cli.py
specktre/colors.py
specktre/specktre.py
specktre/tilings.py
specktre/utils.py
specktre-0.2.0.dist-info/DESCRIPTION.rst
specktre-0.2.0.dist-info/METADATA
specktre-0.2.0.dist-info/RECORD
specktre-0.2.0.dist-info/WHEEL
specktre-0.2.0.dist-info/entry_points.txt
specktre-0.2.0.dist-info/metadata.json
specktre-0.2.0.dist-info/top_level.txt
