Metadata-Version: 2.0
Name: specktre
Version: 0.2.0
Summary: A tool for creating wallpapers with Python
Home-page: https://github.com/alexwlchan/specktre
Author: Alex Chan
Author-email: alex@alexwlchan.net
License: MIT
Keywords: images wallpaper
Platform: UNKNOWN
Classifier: Development Status :: 5 - Production/Stable
Classifier: Intended Audience :: Other Audience
Classifier: License :: OSI Approved :: MIT License
Classifier: Programming Language :: Python :: 2
Classifier: Programming Language :: Python :: 2.7
Classifier: Programming Language :: Python :: 3
Classifier: Programming Language :: Python :: 3.3
Classifier: Programming Language :: Python :: 3.4
Classifier: Programming Language :: Python :: 3.5
Requires-Dist: docopt
Requires-Dist: Pillow
